VortexGPT/__init__.py
VortexGPT/AsyncClient/__init__.py
VortexGPT/AsyncClient/alpaca_7b.py
VortexGPT/AsyncClient/falcon_40b.py
VortexGPT/AsyncClient/gpt3.py
VortexGPT/AsyncClient/gpt4.py
VortexGPT/AsyncClient/pollinations.py
VortexGPT/AsyncClient/prodia.py
VortexGPT/Client/__init__.py
VortexGPT/Client/alpaca_7b.py
VortexGPT/Client/falcon_40b.py
VortexGPT/Client/gpt3.py
VortexGPT/Client/gpt4.py
VortexGPT/Client/pollinations.py
VortexGPT/Client/prodia.py
VortexGPT-0.1.dist-info/LICENSE
VortexGPT-0.1.dist-info/METADATA
VortexGPT-0.1.dist-info/WHEEL
VortexGPT-0.1.dist-info/top_level.txt
VortexGPT-0.1.dist-info/RECORD
