Metadata-Version: 2.1
Name: VortexGPT
Version: 0.1
Summary: VORTEX provides free access to text and image generation models.
Home-page: https://github.com/HelpingAI/VORTEX
Author: OEvortex
License: GPLv3
Project-URL: Source, https://github.com/Ruu3f/freeGPT
Keywords: artificial-intelligence,machine-learning,deep-learning,gpt4free,gpt4all,freegpt,chatgpt,python,llama,llm,nlp,gpt,ai
Classifier: Development Status :: 5 - Production/Stable
Classifier: Intended Audience :: Developers
Classifier: License :: OSI Approved :: GNU General Public License v2 (GPLv2)
Classifier: Natural Language :: English
Classifier: Programming Language :: Python :: 3
Classifier: Programming Language :: Python :: 3.7
Classifier: Programming Language :: Python :: 3.8
Classifier: Programming Language :: Python :: 3.9
Classifier: Programming Language :: Python :: 3.10
Classifier: Programming Language :: Python :: 3.11
Classifier: Programming Language :: Python :: Implementation :: CPython
Classifier: Programming Language :: Python :: Implementation :: PyPy
Requires-Python: >=3.6
License-File: LICENSE
Requires-Dist: aiohttp
Requires-Dist: requests
Requires-Dist: curl-cffi
